appcli/cli_builder.py
appcli/configuration_manager.py
appcli/dev_mode.py
appcli/functions.py
appcli/keycloak_manager.py
appcli/logger.py
appcli/orchestrators.py
appcli/string_transformer.py
appcli/variables_manager.py
appcli/backup_manager/backup_manager.py
appcli/backup_manager/remote_strategy.py
appcli/commands/appcli_command.py
appcli/commands/backup_manager_cli.py
appcli/commands/configure_cli.py
appcli/commands/configure_template_cli.py
appcli/commands/debug_cli.py
appcli/commands/encrypt_cli.py
appcli/commands/init_cli.py
appcli/commands/install_cli.py
appcli/commands/launcher_cli.py
appcli/commands/migrate_cli.py
appcli/commands/service_cli.py
appcli/commands/task_cli.py
appcli/commands/version_cli.py
appcli/common/data_class_extensions.py
appcli/configuration/configuration_dir_state.py
appcli/crypto/cipher.py
appcli/crypto/crypto.py
appcli/git_repositories/git_repositories.py
appcli/models/cli_context.py
appcli/models/configuration.py
appcli/templates/__init__.py
appcli/templates/installer.j2
appcli/templates/launcher.j2
bsl_appcli-3.3.0.dist-info/METADATA
bsl_appcli-3.3.0.dist-info/WHEEL
bsl_appcli-3.3.0.dist-info/licenses/LICENSE
bsl_appcli-3.3.0.dist-info/RECORD
