Metadata-Version: 2.4
Name: bsl-appcli
Version: 3.3.0
Summary: A library for adding CLI interfaces to applications in the brightSPARK Labs style.
Project-URL: Homepage, https://www.brightsparklabs.com
Project-URL: Repository, https://github.com/brightsparklabs/appcli
Project-URL: Changelog, https://github.com/brightsparklabs/appcli/blob/master/CHANGELOG.md
Author-email: brightSPARK Labs <enquire@brightsparklabs.com>
License: MIT License
License-File: LICENSE
Classifier: License :: OSI Approved :: MIT License
Classifier: Operating System :: POSIX :: Linux
Classifier: Programming Language :: Python :: 3
Requires-Python: >=3.12.3
Requires-Dist: boto3==1.37.24
Requires-Dist: click==8.1.8
Requires-Dist: coloredlogs==15.0.1
Requires-Dist: cronex==0.1.3.1
Requires-Dist: dataclasses-json==0.5.7
Requires-Dist: deepdiff==8.4.2
Requires-Dist: gitpython==3.1.44
Requires-Dist: jinja2==3.1.6
Requires-Dist: jsonschema==4.23.0
Requires-Dist: pycryptodome==3.22.0
Requires-Dist: pydantic==2.11.1
Requires-Dist: pyfiglet==1.0.2
Requires-Dist: python-keycloak==3.12.0
Requires-Dist: python-slugify==8.0.4
Requires-Dist: ruamel-yaml==0.18.10
Requires-Dist: tabulate==0.9.0
